{
  "s100001": {
    "allDrop": 0,
    "dropNum": 5,
    "noRepeat": 0,
    "description": "m里掉落n个,根据权重随机掉落n次,结果可重复",
    "items": [
      {
        "itemId": 1,
        "itemNum": 1,
        "percent": 8
      },
      {
        "itemId": 2,
        "itemNum": 1,
        "percent": 3
      },
      {
        "itemId": 3,
        "itemNum": 1,
        "percent": 4
      },
      {
        "itemId": 4,
        "itemNum": 1,
        "percent": 3
      }
    ]
  },
  "s100002": {
    "allDrop": 0,
    "dropNum": 3,
    "noRepeat": 1,
    "description": "m里掉落n个, m > n, 结果不可重复.单次掉落后重新计算权重",
    "items": [
      {
        "itemId": 5,
        "itemNum": 1,
        "percent": 3
      },
      {
        "itemId": 6,
        "itemNum": 1,
        "percent": 3
      },
      {
        "itemId": 7,
        "itemNum": 1,
        "percent": 5
      },
      {
        "itemId": 8,
        "itemNum": 1,
        "percent": 5
      },
      {
        "itemId": 9,
        "itemNum": 1,
        "percent": 2
      }
    ]
  },
  "s100003": {
    "allDrop": 1,
    "dropNum": 0,
    "noRepeat": 0,
    "description": "m里全部掉落",
    "items": [
      {
        "itemId": 10,
        "itemNum": 1,
        "percent": 5
      }
    ]
  },
  "s100004": {
    "allDrop": 1,
    "dropNum": 0,
    "noRepeat": 0,
    "description": "m里全部掉落",
    "items": [
      {
        "itemId": 16,
        "itemNum": 1,
        "percent": 8
      },
      {
        "itemId": 17,
        "itemNum": 1,
        "percent": 3
      },
      {
        "itemId": 18,
        "itemNum": 1,
        "percent": 2
      },
      {
        "itemId": 19,
        "itemNum": 1,
        "percent": 4
      },
      {
        "itemId": 20,
        "itemNum": 1,
        "percent": 3
      },
      {
        "itemId": 21,
        "itemNum": 1,
        "percent": 8
      },
      {
        "itemId": 22,
        "itemNum": 1,
        "percent": 4
      }
    ]
  }
}